sonyapilib/device.py
sonyapilib/ssdp.py
sonyapilib/xml_helper.py
sonyapilib-0.4.5.dist-info/LICENCE
sonyapilib-0.4.5.dist-info/METADATA
sonyapilib-0.4.5.dist-info/WHEEL
sonyapilib-0.4.5.dist-info/top_level.txt
sonyapilib-0.4.5.dist-info/RECORD
